pypre/__init__.py
pypre/directives.py
pypre/parse.py
pypre-0.3.0.dist-info/DESCRIPTION.rst
pypre-0.3.0.dist-info/METADATA
pypre-0.3.0.dist-info/RECORD
pypre-0.3.0.dist-info/WHEEL
pypre-0.3.0.dist-info/entry_points.txt
pypre-0.3.0.dist-info/metadata.json
pypre-0.3.0.dist-info/top_level.txt
