Metadata-Version: 2.0
Name: pypre
Version: 0.3.0
Summary: A Python 3 Pre-processor
Home-page: https://github.com/Sensibility/pypre
Author: ocket8888
Author-email: ocket8888@gmail.com
License: UNKNOWN
Keywords: preprocessor analysis static compile process preprocess pre-process
Platform: UNKNOWN
Classifier: Development Status :: 4 - Beta
Classifier: Intended Audience :: Developers
Classifier: Intended Audience :: Information Technology
Classifier: Topic :: Utilities
Classifier: License :: OSI Approved :: GNU Lesser General Public License v3 or later (LGPLv3+)
Classifier: Environment :: Console
Classifier: Operating System :: OS Independent
Classifier: Programming Language :: Python :: Implementation :: CPython
Classifier: Programming Language :: Python :: Implementation :: PyPy
Classifier: Programming Language :: Python :: 3 :: Only
Requires-Python: ~=3.0
Requires-Dist: setuptools
Requires-Dist: typing
